seqchromloader/__init__.py
seqchromloader/loader.py
seqchromloader/utils.py
seqchromloader/writer.py
seqchromloader-0.9.3.dist-info/METADATA
seqchromloader-0.9.3.dist-info/WHEEL
seqchromloader-0.9.3.dist-info/top_level.txt
seqchromloader-0.9.3.dist-info/RECORD
